tort/__init__.py
tort/handler.py
tort/logger.py
tort/request_id.py
tort/version.py
tort/test/__init__.py
tort/test/import_test.py
tort/test/runtests.py
tort/util/__init__.py
tort/util/parse.py
tort/util/request.py
tort/util/xml_etree.py
tort-0.5.9.dist-info/METADATA
tort-0.5.9.dist-info/WHEEL
tort-0.5.9.dist-info/top_level.txt
tort-0.5.9.dist-info/RECORD
