Metadata-Version: 2.1
Name: tort
Version: 0.5.9
Summary: Tort - Tornado framework helper functions
Home-page: https://github.com/glibin/tort
Download-URL: https://github.com/glibin/tort/tarball/0.5.9
Classifier: License :: OSI Approved :: MIT License
Classifier: Programming Language :: Python
Classifier: Programming Language :: Python :: 3.7
Requires-Python: >= 3.7
Requires-Dist: tornado (>=6.0.1)
